questrade_api/__init__.py
questrade_api/auth.py
questrade_api/enumerations.py
questrade_api/questrade.cfg
questrade_api/questrade.py
questrade_api-1.0.3.dist-info/LICENSE
questrade_api-1.0.3.dist-info/METADATA
questrade_api-1.0.3.dist-info/WHEEL
questrade_api-1.0.3.dist-info/top_level.txt
questrade_api-1.0.3.dist-info/RECORD
