Metadata-Version: 2.1
Name: questrade-api
Version: 1.0.3
Summary: Python3 Questrade API Wrapper
Home-page: https://github.com/tgardiner/questrade_api
Author: Tom Gardiner
Author-email: tom@teppen.io
License: MIT
Platform: UNKNOWN
Classifier: Programming Language :: Python :: 3
Classifier: License :: OSI Approved :: MIT License
Classifier: Operating System :: OS Independent
Requires-Python: >=3
